traceai_openai_agents/__init__.py
traceai_openai_agents/_processor.py
traceai_openai_agents/package.py
traceai_openai_agents/py.typed
traceai_openai_agents/version.py
traceai_openai_agents-0.1.5.dist-info/METADATA
traceai_openai_agents-0.1.5.dist-info/WHEEL
traceai_openai_agents-0.1.5.dist-info/RECORD
